cypher_query_loader/__init__.py
cypher_query_loader/query_objects.py
cypher_query_loader-0.1.2.dist-info/LICENSE
cypher_query_loader-0.1.2.dist-info/METADATA
cypher_query_loader-0.1.2.dist-info/WHEEL
cypher_query_loader-0.1.2.dist-info/RECORD
