Metadata-Version: 2.1
Name: cypher_query_loader
Version: 0.1.2
Summary: Load cypher queries from a directory as python string objects.
License: MIT
Author: Ted Johnson
Author-email: ted.johnson87@gmail.com
Requires-Python: >=3.9,<4.0
Classifier: License :: OSI Approved :: MIT License
Classifier: Programming Language :: Python :: 3
Classifier: Programming Language :: Python :: 3.9
Classifier: Programming Language :: Python :: 3.10
Classifier: Programming Language :: Python :: 3.11
Requires-Dist: pre-commit (>=4.2.0,<5.0.0)
